{
  "slug": "calculadora-emision-co2-auto-combustible",
  "title": "Calculadora Emisión de CO2 por Auto y Combustible | Hacé Cuentas",
  "h1": "Calculadora Emisión de CO2 por Auto y Combustible",
  "description": "Emision co2 auto: calculá cuánto CO2 emite tu auto por kilómetro y por año según el tipo de combustible y el consumo. Huella de carbono vehicular Argentina",
  "category": "automotor",
  "icon": "🚗",
  "formulaId": "emision-co2-auto-combustible",
  "seoKeywords": [
    "emision co2 auto",
    "huella carbono auto",
    "cuanto co2 emite un auto",
    "emisiones auto por km",
    "contaminacion auto combustible"
  ],
  "intro": "¿Cuánto **CO2** genera tu auto? Cada litro de nafta quemado produce aproximadamente **2.31 kg de CO2**, y cada litro de diésel **2.68 kg**. Con esta calculadora ingresás el consumo de tu auto y los kilómetros anuales para saber tu **huella de carbono vehicular**. Un auto mediano naftero emite entre **150 y 200 g CO2/km**. Conocer tu huella es el primer paso para **reducirla** o **compensarla**.",
  "keyTakeaway": "**Cada litro de nafta = 2.31 kg CO2. Un auto mediano emite ~150-200 g CO2/km.** En 15.000 km/año: 2.5-3.5 toneladas de CO2. Un auto eléctrico (con energía limpia): 0 emisiones directas.",
  "useCases": [
    "Calcular la huella de carbono de tu auto por año.",
    "Comparar emisiones entre nafta, diésel, GNC y eléctrico.",
    "Estimar el beneficio ambiental de cambiar a un auto más eficiente.",
    "Calcular la compensación de carbono necesaria para tus viajes.",
    "Reportar emisiones vehiculares para informes de sustentabilidad."
  ],
  "fields": [
    {
      "id": "consumoL100km",
      "label": "Consumo de combustible (L/100km)",
      "type": "number",
      "placeholder": "10",
      "min": 2,
      "max": 30,
      "step": 0.5,
      "required": true,
      "help": "Consumo real de tu auto en litros cada 100 km."
    },
    {
      "id": "tipoCombustible",
      "label": "Tipo de combustible (1=Nafta, 2=Diésel, 3=GNC)",
      "type": "number",
      "placeholder": "1",
      "min": 1,
      "max": 3,
      "step": 1,
      "required": true,
      "help": "1=Nafta/gasolina, 2=Gasoil/diésel, 3=GNC."
    },
    {
      "id": "kmAnuales",
      "label": "Kilómetros anuales",
      "type": "number",
      "placeholder": "15000",
      "min": 1000,
      "step": 1000,
      "required": true
    }
  ],
  "dataUpdate": {
    "frequency": "never",
    "lastUpdated": "2026-04-15",
    "source": null,
    "sourceUrl": null,
    "updateType": "manual",
    "notes": "Factores de emisión estándar IPCC para combustibles fósiles"
  },
  "outputs": [
    {
      "id": "co2PorKm",
      "label": "Emisión por km",
      "format": "number",
      "primary": true,
      "suffix": " g CO2/km"
    },
    {
      "id": "co2Anual",
      "label": "Emisión anual total",
      "format": "number",
      "suffix": " kg CO2"
    },
    {
      "id": "co2AnualTon",
      "label": "Emisión anual (toneladas)",
      "format": "number",
      "suffix": " ton CO2"
    },
    {
      "id": "detalle",
      "label": "Detalle",
      "format": "text"
    }
  ],
  "example": {
    "title": "Ejemplo: Auto naftero, 10 L/100km, 15.000 km/año",
    "steps": [
      "**Consumo**: 10 L/100km de nafta.",
      "**Factor**: 2.31 kg CO2 por litro de nafta.",
      "**CO2/km**: 10/100 × 2.31 = 0.231 kg = **231 g CO2/km**.",
      "**CO2/año**: 0.231 × 15.000 = **3.465 kg** = **3.47 toneladas**."
    ],
    "result": "Tu auto emite **231 g CO2/km** y **3.47 toneladas de CO2 por año**. Es como quemar ~1.500 litros de nafta anuales."
  },
  "explanation": "## Factores de emisión por tipo de combustible\n\n| Combustible | CO2 por litro/m³ | g CO2/km (consumo 10) |\n|---|---|---|\n| Nafta/gasolina | 2.31 kg/L | 231 g/km |\n| Diésel/gasoil | 2.68 kg/L | 268 g/km |\n| GNC | 1.88 kg/m³ | 244 g/km (13 m³/100km) |\n| Eléctrico | 0 directas | 0 g/km (en el caño) |\n\nNota: el eléctrico tiene emisiones **indirectas** por la generación eléctrica, que en Argentina es ~40% fósil.\n\n## Emisiones típicas por tipo de auto\n\n| Auto | Consumo | CO2/km |\n|---|---|---|\n| City car naftero | 7 L/100km | 162 g/km |\n| Hatchback naftero | 9 L/100km | 208 g/km |\n| Sedán naftero | 10 L/100km | 231 g/km |\n| SUV naftero | 12 L/100km | 277 g/km |\n| Pickup diésel | 10 L/100km | 268 g/km |\n| Híbrido | 5 L/100km | 116 g/km |\n| Eléctrico | — | 0 g/km directas |\n\n## Contexto: ¿cuánto es 3 toneladas de CO2?\n\n- Es como **1.5 vuelos Buenos Aires - Madrid** (ida y vuelta).\n- Equivale a la absorción anual de **~150 árboles adultos**.\n- La huella promedio de un argentino es **~4.5 ton CO2/año** (total, no solo auto).\n- El auto suele representar el **30-50%** de la huella personal.\n\n## Cómo reducir las emisiones de tu auto\n\n1. **Manejá eficientemente** (sin acelerones): reduce 15-20%.\n2. **Mantené el auto** (filtros, bujías, neumáticos inflados): 5-10%.\n3. **Usá menos el auto** (bici, transporte público, home office).\n4. **Compartí viajes** (carpooling): divide las emisiones por persona.\n5. **Pasá a GNC**: reduce ~20-30% vs nafta.\n6. **Comprá un auto más eficiente** o híbrido.\n7. **Compensá**: comprá créditos de carbono (desde $5.000/ton).\n\n## Normas de emisiones en Argentina\n\nArgentina sigue las normas **Euro** (europea):\n- Autos nuevos deben cumplir **Euro 5** o superior.\n- Límite: 130-160 g CO2/km promedio para flotas nuevas.\n- Los autos más contaminantes pueden tener restricciones futuras.\n\n## Emisiones well-to-wheel vs tank-to-wheel\n\n- **Tank-to-wheel**: emisiones del caño de escape (lo que calcula esta herramienta).\n- **Well-to-wheel**: incluye extracción, refinado y transporte del combustible (+20-25%).\n- Para autos eléctricos, las emisiones son 100% well-to-wheel (de la central eléctrica).",
  "faq": [
    {
      "q": "¿Cuánto CO2 emite un auto promedio por kilómetro?",
      "a": "Un auto naftero promedio en Argentina emite entre **180 y 250 g CO2/km** dependiendo del tamaño y consumo. Un city car eficiente: ~160 g/km. Un SUV grande: ~280 g/km. Un auto eléctrico: 0 emisiones directas. El promedio del parque automotor argentino ronda los **200-220 g/km**."
    },
    {
      "q": "¿El diésel contamina más que la nafta?",
      "a": "El diésel emite más **CO2 por litro** (2.68 vs 2.31 kg), pero como los motores diésel son **más eficientes** (consumen menos litros), las emisiones por km suelen ser similares o incluso menores. Sin embargo, el diésel emite más **partículas finas (PM2.5)** y **NOx**, que son peores para la salud respiratoria."
    },
    {
      "q": "¿Los autos eléctricos realmente no contaminan?",
      "a": "No emiten CO2 por el caño de escape (**0 emisiones directas**), pero la electricidad que usan se genera en centrales que pueden ser fósiles. En Argentina, ~40% de la electricidad viene de gas natural. Un EV en Argentina emite indirectamente ~**60-80 g CO2/km**. En países con energía 100% renovable: ~0 g/km."
    },
    {
      "q": "¿Cuántas toneladas de CO2 emite un auto por año?",
      "a": "Con 15.000 km/año y consumo de 10 L/100km de nafta: **~3.5 toneladas de CO2** por año. Con diésel al mismo consumo: ~4.0 toneladas. Un auto muy eficiente (híbrido, 5 L/100km): ~1.7 toneladas. La huella total de un argentino promedio es ~4.5 toneladas."
    },
    {
      "q": "¿Cómo compenso las emisiones de mi auto?",
      "a": "Podés comprar **créditos de carbono** en plataformas certificadas (desde $5.000-$10.000 por tonelada de CO2). Con 3.5 ton/año, compensar cuesta ~**$25.000-$35.000/año**. También podés plantar árboles: un árbol adulto absorbe ~**22 kg CO2/año**, así que necesitarías ~160 árboles para compensar un auto."
    },
    {
      "q": "¿El GNC es más limpio que la nafta?",
      "a": "Sí, el GNC emite aproximadamente un **20-25% menos de CO2** por unidad de energía que la nafta. También emite menos partículas y contaminantes locales. Por eso es una alternativa \"más limpia\" (no limpia del todo). Además, el GNC produce menos hollín, lo que extiende la vida del motor."
    },
    {
      "q": "¿Conviene un híbrido en Argentina?",
      "a": "Ambientalmente sí: consume **40-50% menos** que un naftero puro. Económicamente, depende: los híbridos son **más caros de comprar** pero ahorran en nafta. En ciudad, donde más se aprovecha la regeneración, un híbrido como el Toyota Corolla HEV puede hacer **4-5 L/100km** vs 8-9 del naftero."
    }
  ],
  "sources": [
    {
      "name": "IPCC — Factores de emisión de combustibles",
      "url": "https://www.ipcc.ch/"
    },
    {
      "name": "Secretaría de Ambiente — Argentina",
      "url": "https://www.argentina.gob.ar/ambiente"
    }
  ],
  "relatedSlugs": [],
  "howToSteps": [
    {
      "name": "Ingresá consumo de combustible",
      "text": "Ingresá consumo de combustible (L/100km) (ej: 10). Es consumo real de tu auto en litros cada 100 km."
    },
    {
      "name": "Ingresá tipo de combustible",
      "text": "Ingresá tipo de combustible (1=Nafta, 2=Diésel, 3=GNC) (ej: 1). Es 1=Nafta/gasolina, 2=Gasoil/diésel, 3=GNC."
    },
    {
      "name": "Ingresá kilómetros anuales",
      "text": "Ingresá kilómetros anuales (ej: 15000). Es el valor de kilómetros anuales."
    },
    {
      "name": "Hacé click en Calcular",
      "text": "Presioná el botón \"Calcular\" para obtener el resultado. La calculadora procesa los datos al instante."
    },
    {
      "name": "Revisá los resultados",
      "text": "Revisá los resultados que aparecen debajo del formulario. Podés modificar cualquier dato y volver a calcular."
    }
  ]
}
