{
  "slug": "calculadora-cuenta-afc-ahorro-fomento-construccion-colombia",
  "title": "Calculadora Cuenta AFC Colombia 2026 | Hacé Cuentas",
  "h1": "Cuenta AFC Colombia (vivienda)",
  "description": "Calcula tu ahorro fiscal con Cuenta AFC: aportes deducibles hasta 3.800 UVT, retiros exentos vivienda. Comparativa con FNA 2026.",
  "category": "finanzas",
  "audience": "CO",
  "icon": "🏠",
  "formulaId": "cuenta-afc-ahorro-fomento-construccion-colombia",
  "intro": "La **Cuenta AFC (Ahorro Fomento Construcción)** es un mecanismo de ahorro incentivado en Colombia para la adquisición, construcción o mejora de vivienda propia. Los aportes son deducibles de la renta hasta el **30% del ingreso laboral** (máximo 3.800 UVT anuales ≈ $157 millones en 2026). Los retiros para vivienda están **exentos de impuesto a la renta**. Esta calculadora estima tu beneficio fiscal anual y acumulado.",
  "keyTakeaway": "Con aportes mensuales a AFC y tarifa marginal 28%, ahorras hasta $11.2 millones anuales en impuestos; capital exento retiros vivienda.",
  "useCases": [
    "Trabajador dependiente que ahorra para compra vivienda propia",
    "Independiente que quiere deducir aportes vivienda en declaración renta",
    "Comparar beneficio fiscal AFC vs FNA tradicional",
    "Planificar aporte máximo permitido por ley (3.800 UVT)",
    "Estimar retiro exento para enganche o construcción"
  ],
  "fields": [
    {
      "id": "aporte_mensual",
      "label": "Aporte mensual a AFC ($)",
      "type": "number",
      "placeholder": "2500000",
      "min": 0,
      "max": 50000000,
      "step": 100000,
      "tooltip": "Cantidad mensual que aportas a tu cuenta AFC. Máximo anual: 3.800 UVT (≈$157M en 2026)."
    },
    {
      "id": "tarifa_marginal",
      "label": "Tarifa marginal impuesto renta (%)",
      "type": "select",
      "options": [
        {
          "value": "0",
          "label": "0% (sin obligación tributaria)"
        },
        {
          "value": "5",
          "label": "5%"
        },
        {
          "value": "12",
          "label": "12%"
        },
        {
          "value": "19",
          "label": "19%"
        },
        {
          "value": "25",
          "label": "25%"
        },
        {
          "value": "28",
          "label": "28%"
        },
        {
          "value": "33",
          "label": "33%"
        },
        {
          "value": "37",
          "label": "37%"
        },
        {
          "value": "39",
          "label": "39%"
        }
      ],
      "default": "28",
      "tooltip": "Tu tarifa marginal según declaración renta 2025. Determina el ahorro fiscal por cada $ aportado."
    },
    {
      "id": "años_proyeccion",
      "label": "Años de proyección",
      "type": "number",
      "placeholder": "5",
      "min": 1,
      "max": 40,
      "step": 1,
      "default": 5,
      "tooltip": "Período para calcular capital acumulado y ahorro fiscal acumulado."
    },
    {
      "id": "rentabilidad_anual",
      "label": "Rentabilidad anual esperada (%)",
      "type": "number",
      "placeholder": "6.5",
      "min": 0,
      "max": 15,
      "step": 0.5,
      "default": 6.5,
      "tooltip": "Retorno promedio anual de fondos AFC (histórico 5-8%; conservador: 6.5%)."
    }
  ],
  "outputs": [
    {
      "id": "aporte_anual",
      "label": "Aporte anual",
      "format": "currency",
      "tooltip": "Total aportado en 12 meses sin incluir rentabilidad."
    },
    {
      "id": "aporte_anual_permitido",
      "label": "Límite legal anual (3.800 UVT)",
      "format": "currency",
      "tooltip": "Máximo deducible: 3.800 UVT ≈ $157.2 millones en 2026. Aportes superiores no generan beneficio fiscal."
    },
    {
      "id": "aporte_deducible",
      "label": "Aporte deducible real",
      "format": "currency",
      "tooltip": "Menor entre: aporte anual y 3.800 UVT. Base para cálculo impuesto ahorrado."
    },
    {
      "id": "ahorro_fiscal_anual",
      "label": "Ahorro fiscal anual",
      "format": "currency",
      "tooltip": "Impuesto ahorrado en año 1 = aporte deducible × tarifa marginal."
    },
    {
      "id": "capital_acumulado_sin_rentabilidad",
      "label": "Capital acumulado (sin rentabilidad)",
      "format": "currency",
      "tooltip": "Suma de aportes durante los años proyectados."
    },
    {
      "id": "capital_acumulado_con_rentabilidad",
      "label": "Capital acumulado (con rentabilidad)",
      "format": "currency",
      "tooltip": "Aportes más intereses compuestos a la rentabilidad anual esperada."
    },
    {
      "id": "ahorro_fiscal_acumulado",
      "label": "Ahorro fiscal acumulado",
      "format": "currency",
      "tooltip": "Total impuestos ahorrados en los años proyectados (asumiendo misma tarifa marginal)."
    },
    {
      "id": "rentabilidad_acumulada",
      "label": "Rentabilidad generada",
      "format": "currency",
      "tooltip": "Ganancias por inversión de aportes: capital con rentabilidad − capital sin rentabilidad."
    },
    {
      "id": "patrimonio_total",
      "label": "Patrimonio total disponible",
      "format": "currency",
      "tooltip": "Capital acumulado + ahorro fiscal acumulado (estimación beneficio neto total)."
    },
    {
      "id": "aviso_limite",
      "label": "Estado deducibilidad",
      "format": "text",
      "tooltip": "Indica si aporte supera límite legal o se ajusta correctamente."
    }
  ],
  "explanation": "## ¿Qué es la Cuenta AFC?\n\nLa Cuenta AFC (Ahorro Fomento Construcción) es un mecanismo de ahorro incentivado en Colombia para adquirir o mejorar vivienda propia. Permite deducir aportes hasta 3.800 UVT anuales del impuesto a la renta, generando ahorros fiscales del 28% según tu tarifa. Los retiros para compra de vivienda están exentos de impuesto.\n\n## Cómo se calcula la Cuenta AFC Colombia\n\nLa **Cuenta AFC** es un fondo de ahorro dedicado creado por la **Ley 1557 de 2012** (Colombia). Funciona como sistema de capitalización individual con beneficios tributarios específicos para vivienda.\n\n### Fórmula básica\n\n**Aporte anual:** \n```\naporte_anual = aporte_mensual × 12\n```\n\n**Aporte deducible (limitado por ley):**\n```\naporte_deducible = MIN(aporte_anual, 3.800 UVT)\nDonde: 3.800 UVT 2026 ≈ $157.200.000 (1 UVT 2026 = $41.368)\n```\n\n**Ahorro fiscal anual (año 1):**\n```\nahorro_fiscal_anual = aporte_deducible × (tarifa_marginal / 100)\n```\n\n**Capital acumulado (sin rentabilidad):**\n```\ncapital_sin_renta = aporte_anual × años_proyeccion\n```\n\n**Capital acumulado (con rentabilidad - interés compuesto):**\n```\ncapital_con_renta = aporte_anual × [((1 + r)^n - 1) / r]\nDonde: r = rentabilidad_anual / 100\n       n = años_proyeccion\n```\n\n**Ahorro fiscal acumulado (manteniendo tarifa marginal constante):**\n```\nahorro_fiscal_acumulado = ahorro_fiscal_anual × años_proyeccion\n```\n\n**Rentabilidad generada:**\n```\nrentabilidad = capital_con_renta - capital_sin_renta\n```\n\n### Ejemplo práctico\n\n**Supuestos:**\n- Aporte mensual: $2.500.000\n- Tarifa marginal: 28%\n- Rentabilidad anual: 6.5%\n- Horizonte: 5 años\n\n**Cálculos:**\n\n| Concepto | Valor | Nota |\n|----------|-------|------|\n| Aporte anual | $30.000.000 | 2.5M × 12 |\n| Límite legal (3.800 UVT) | $157.200.000 | Vigencia 2026 |\n| Aporte deducible | $30.000.000 | MIN(30M, 157.2M) |\n| Ahorro fiscal año 1 | $8.400.000 | 30M × 28% |\n| Capital 5 años (sin renta) | $150.000.000 | 30M × 5 |\n| Capital 5 años (con renta 6.5%) | $168.747.630 | Fórmula interés compuesto |\n| Ahorro fiscal acumulado (5 años) | $42.000.000 | 8.4M × 5 |\n| Rentabilidad generada | $18.747.630 | 168.7M − 150M |\n| **Patrimonio total** | **$260.747.630** | Capital + ahorro fiscal |\n\n### Beneficios tributarios AFC\n\n1. **Deducción en renta:** Hasta 30% del ingreso laboral, máximo 3.800 UVT/año.\n2. **Exención de retiros:** Dinero retirado para vivienda (compra, construcción, mejora, pago crédito) está **exento de impuesto a la renta**.\n3. **Rentabilidad no tributada:** Intereses generados dentro de la cuenta no pagan impuesto de renta mientras permanezcan ahí.\n4. **Portabilidad:** Puedes cambiar de administrador (banco/AFP) sin penalización.\n\n### Limitaciones y consideraciones\n\n- **Límite anual:** No puedes deducir más de 3.800 UVT; excesos se pierden.\n- **Destino vivienda:** Para aprovechar exención, retiros deben ser para vivienda principal del titular, cónyuge o hijos.\n- **Rentabilidad variable:** Fondos tiene rentabilidades que fluctúan; estimación es conservadora (6.5%).\n- **Sin reajuste UVT en cálculo:** Aquí usamos UVT 2026 fija; en realidad reajusta anualmente.\n- **Imposición sobre exceso:** Dinero aportado y no deducido paga impuesto normal al retirar (a menos que sea para vivienda).\n- **Comisiones:** Bancos/AFPs cobran comisión anual (~0.5-1%); no incluidas en estimación.\n- **Dependencia de tarifa marginal:** Beneficio fiscal solo si declaras renta; trabajadores sin obligación tributaria no se benefician.\n\n## Comparativa AFC vs FNA\n\n| Aspecto | **AFC** | **FNA** |\n|--------|--------|--------|\n| Deducción renta | Hasta 30% ingreso (3.800 UVT) | No hay |\n| Exención retiro vivienda | Sí, 100% | Tributado como renta |\n| Rentabilidad | 5-8% histórico | Varía (fondos mixtos) |\n| Gestor | Banco/AFP con licencia AFC | Banco/AFP genérico |\n| Costo comisión | 0.5-1% anual | 0.3-0.8% anual |\n| Ideal para | Trabajadores en renta alta que compran vivienda | Ahorro flexible sin beneficio fiscal |\n\n",
  "faq": [
    {
      "q": "¿Cuál es el límite máximo de aporte deducible en AFC 2026?",
      "a": "El límite es **3.800 UVT anuales**, equivalente a aproximadamente **$157.2 millones en 2026** (UVT 2026 = $41.368). Si aportas más, el exceso no es deducible en renta, aunque permanece en tu cuenta."
    },
    {
      "q": "¿Puedo deducir mis aportes AFC si soy trabajador independiente?",
      "a": "Sí. Si eres independiente y declaras renta, puedes deducir aportes AFC hasta el 30% de tu ingreso laboral o 3.800 UVT, lo que sea menor. Debes reportarlo en el formulario 210 o 100 de DIAN con comprobante del fondo."
    },
    {
      "q": "¿Qué pasa si retiro dinero AFC para algo que no sea vivienda?",
      "a": "Si retiras para fines diferentes a compra, construcción, mejora o pago de crédito de vivienda principal (tuya, cónyuge o hijos), el dinero retirado **tributa como renta ordinaria** según tu tarifa marginal. Los aportes ya deducidos se consideran ingreso gravado."
    },
    {
      "q": "¿Los intereses generados en AFC pagan impuesto mientras están en la cuenta?",
      "a": "No. La rentabilidad acumulada dentro de la cuenta AFC está **libre de impuesto sobre la renta** mientras no retires. Al retirar para vivienda, sale exenta; si retiras para otros fines, tributa."
    },
    {
      "q": "¿Puedo trasferir mi saldo AFC a otro banco?",
      "a": "Sí, es **portabilidad gratuita**. Puedes cambiar de administrador (banco/AFP) sin perder beneficios ni pagar penalización. Contacta al banco nuevo y ellos gestionan la transferencia."
    },
    {
      "q": "¿Cuál es la rentabilidad histórica de los fondos AFC?",
      "a": "Según **Superintendencia Financiera de Colombia**, fondos AFC han rentado en promedio **5-8% anual** en últimos 5 años, dependiendo del fondo (conservador, moderado o de crecimiento). Esta calculadora usa 6.5% como estimación conservadora."
    },
    {
      "q": "¿Si no tengo obligación de declarar renta, me sirve la deducción AFC?",
      "a": "No. La deducción AFC solo beneficia a quienes declaran renta y tienen tarifa marginal positiva. Si no estás obligado a declarar, no obtienes ahorro fiscal, aunque sí puedes ahorrar en la cuenta y usar exención al retirar para vivienda."
    },
    {
      "q": "¿Qué documentos necesito para validar deducción AFC en DIAN?",
      "a": "Guarda **certificado anual del fondo AFC** con: tu nombre, cédula, aportes mensuales, total anual, rentabilidad generada. Cuando presentes declaración de renta, adjunta este comprobante. DIAN puede solicitar verificación."
    },
    {
      "q": "¿Cuál es la diferencia entre AFC y ahorro en banco corriente?",
      "a": "AFC ofrece: (1) **deducción fiscal** en renta, (2) **exención retiro vivienda**, (3) rentabilidad similar o mejor que CDT. Banco corriente solo genera intereses tributados. AFC es superior si compras vivienda propia."
    },
    {
      "q": "¿Puedo aportar a AFC si tengo crédito hipotecario vigente?",
      "a": "Sí. Incluso es estratégico: aportas a AFC (con deducción), acumulas capital, y cuando termines de pagar la casa, puedes retirar exento para mejoras, ampliación o segunda propiedad. Los aportes no interfieren con crédito existente."
    }
  ],
  "sources": [
    {
      "name": "DIAN - Deducción por aportes AFC",
      "url": "https://www.dian.gov.co/aduanas/franquiciasArancelarias/Paginas/default.aspx",
      "publisher": "DIAN",
      "date": "2026"
    },
    {
      "name": "Ley 1557 de 2012 - Cuenta AFC",
      "url": "https://www.funcionpublica.gov.co/eva/gestornormativo/norma.php?i=47940",
      "publisher": "Función Pública - Rama Legislativa",
      "date": "2012"
    },
    {
      "name": "Superintendencia Financiera - Fondos AFC",
      "url": "https://www.superfinanciera.gov.co/jsp/index.jsf",
      "publisher": "Superfinanciera de Colombia",
      "date": "2026"
    },
    {
      "name": "UVT 2026 - Decreto 1743 de 2023",
      "url": "https://www.dian.gov.co/impuestos/otros-contenidos/Paginas/uvt.aspx",
      "publisher": "DIAN",
      "date": "2026"
    }
  ],
  "dataUpdate": {
    "frequency": "yearly",
    "lastUpdated": "2026-04-28",
    "source": "DIAN - Decretos UVT y normativa tributaria",
    "sourceUrl": "https://www.dian.gov.co/",
    "updateType": "manual",
    "notes": "UVT 2026, tarifas IRPF 2026, límite 3.800 UVT, rentabilidad promedio fondos AFC Superintendencia Financiera."
  },
  "lastReviewed": "2026-04-28"
}
